xir/__init__.py
xir/_version.py
xir/decimal_complex.py
xir/parser.py
xir/program.py
xir/utils.py
xir/validator.py
xir/xir.lark
quantum_xir-0.2.2.dist-info/LICENSE
quantum_xir-0.2.2.dist-info/METADATA
quantum_xir-0.2.2.dist-info/WHEEL
quantum_xir-0.2.2.dist-info/top_level.txt
quantum_xir-0.2.2.dist-info/RECORD
